__init__.py
mathextend/Constant.py
mathextend/Flat_graphics.py
mathextend/Fractions.py
mathextend/Three_dimensional_graphics.py
mathextend/__init__.py
mathextend-1.1.0.dist-info/LICENSE
mathextend-1.1.0.dist-info/METADATA
mathextend-1.1.0.dist-info/WHEEL
mathextend-1.1.0.dist-info/top_level.txt
mathextend-1.1.0.dist-info/RECORD
