Metadata-Version: 2.1
Name: mathextend
Version: 1.1.0
Summary: Extension of a powerful math library
Author-email: xiechenxin <xiechenxin20110311@qq.com>
License: MIT License        
Project-URL: Homepage, https://github.com/xcx-2843604975/mathutil
Project-URL: Bug Tracker, https://github.com/xcx-2843604975/mathutil/issues
Classifier: Programming Language :: Python :: 3
Classifier: License :: OSI Approved :: MIT License
Classifier: Operating System :: OS Independent
Requires-Python: >=3.6
License-File: LICENSE
